[{"code":"017","name":"上鳥羽","name_kana":"ｶﾐﾄﾊﾞ"},{"code":"019","name":"桂","name_kana":"ｶﾂﾗ"},{"code":"033","name":"賀茂","name_kana":"ｶﾓ"},{"code":"036","name":"樫原","name_kana":"ｶﾀｷﾞﾊﾗ"},{"code":"063","name":"亀岡","name_kana":"ｶﾒｵｶ"},{"code":"079","name":"亀岡駅前","name_kana":"ｶﾒｵｶｴｷﾏｴ"},{"code":"082","name":"葛野","name_kana":"ｶﾄﾞﾉ"},{"code":"102","name":"桂坂","name_kana":"ｶﾂﾗｻﾞｶ"},{"code":"108","name":"桂駅前","name_kana":"ｶﾂﾗｴｷﾏｴ"},{"code":"116","name":"上堀川","name_kana":"ｶﾐﾎﾘｶﾜ"},{"code":"118","name":"上桂","name_kana":"ｶﾐｶﾂﾗ"},{"code":"126","name":"加茂町","name_kana":"ｶﾓﾁﾖｳ"},{"code":"148","name":"堅田","name_kana":"ｶﾀﾀ"}]