[{"code":"109","name":"一万","name_kana":"ｲﾁﾏﾝ"},{"code":"136","name":"石井","name_kana":"ｲｼｲ"},{"code":"200","name":"今治","name_kana":"ｲﾏﾊﾞﾘ"},{"code":"210","name":"今治南","name_kana":"ｲﾏﾊﾞﾘﾐﾅﾐ"},{"code":"214","name":"今治市役所出張所","name_kana":"ｲﾏﾊﾞﾘｼﾔｸｼﾖ"},{"code":"265","name":"飯岡","name_kana":"ｲｲｵｶ"},{"code":"307","name":"五十崎","name_kana":"ｲｶｻﾞｷ"},{"code":"310","name":"伊方","name_kana":"ｲｶﾀ"},{"code":"361","name":"岩松","name_kana":"ｲﾜﾏﾂ"},{"code":"605","name":"五日市","name_kana":"ｲﾂｶｲﾁ"},{"code":"788","name":"インターネット","name_kana":"ｲﾝﾀ-ﾈﾂﾄ"}]