[{"code":"005","name":"松前","name_kana":"ﾏﾂﾏｴ"},{"code":"006","name":"森","name_kana":"ﾓﾘ"},{"code":"007","name":"八雲","name_kana":"ﾔｸﾓ"},{"code":"008","name":"長万部","name_kana":"ｵｼﾔﾏﾝﾍﾞ"},{"code":"009","name":"江差","name_kana":"ｴｻｼ"},{"code":"011","name":"手宮","name_kana":"ﾃﾐﾔ"},{"code":"013","name":"余市","name_kana":"ﾖｲﾁ"},{"code":"015","name":"倶知安","name_kana":"ｸﾂﾁﾔﾝ"},{"code":"020","name":"伊達","name_kana":"ﾀﾞﾃ"},{"code":"022","name":"苫小牧北","name_kana":"ﾄﾏｺﾏｲｷﾀ"},{"code":"023","name":"浦河","name_kana":"ｳﾗｶﾜ"},{"code":"024","name":"静内","name_kana":"ｼｽﾞﾅｲ"},{"code":"027","name":"東月寒","name_kana":"ﾋｶﾞｼﾂｷｻﾑ"},{"code":"028","name":"本店","name_kana":"ﾎﾝﾃﾝ"},{"code":"029","name":"すすきの","name_kana":"ｽｽｷﾉ"},{"code":"035","name":"東苗穂","name_kana":"ﾋｶﾞｼﾅｴﾎﾞ"},{"code":"036","name":"光星","name_kana":"ｺｳｾｲ"},{"code":"041","name":"新琴似","name_kana":"ｼﾝｺﾄﾆ"},{"code":"042","name":"豊平","name_kana":"ﾄﾖﾋﾗ"},{"code":"045","name":"白石本郷","name_kana":"ｼﾛｲｼﾎﾝｺﾞｳ"},{"code":"049","name":"屯田","name_kana":"ﾄﾝﾃﾞﾝ"},{"code":"051","name":"北郷","name_kana":"ｷﾀｺﾞｳ"},{"code":"052","name":"発寒","name_kana":"ﾊﾂｻﾑ"},{"code":"053","name":"もみじ台","name_kana":"ﾓﾐｼﾞﾀﾞｲ"},{"code":"055","name":"宮の森","name_kana":"ﾐﾔﾉﾓﾘ"},{"code":"058","name":"当別","name_kana":"ﾄｳﾍﾞﾂ"},{"code":"059","name":"栗山","name_kana":"ｸﾘﾔﾏ"},{"code":"060","name":"美唄","name_kana":"ﾋﾞﾊﾞｲ"},{"code":"061","name":"滝川","name_kana":"ﾀｷｶﾜ"},{"code":"062","name":"砂川","name_kana":"ｽﾅｶﾞﾜ"},{"code":"063","name":"深川","name_kana":"ﾌｶｶﾞﾜ"},{"code":"066","name":"旭川北","name_kana":"ｱｻﾋｶﾜｷﾀ"},{"code":"069","name":"士別","name_kana":"ｼﾍﾞﾂ"},{"code":"070","name":"名寄","name_kana":"ﾅﾖﾛ"},{"code":"071","name":"富良野","name_kana":"ﾌﾗﾉ"},{"code":"073","name":"帯広南","name_kana":"ｵﾋﾞﾋﾛﾐﾅﾐ"},{"code":"074","name":"清水","name_kana":"ｼﾐｽﾞ"},{"code":"075","name":"池田","name_kana":"ｲｹﾀﾞ"},{"code":"077","name":"鳥取","name_kana":"ﾄﾂﾄﾘ"},{"code":"078","name":"釧路十条","name_kana":"ｸｼﾛｼﾞﾕｳｼﾞﾖｳ"},{"code":"079","name":"厚岸","name_kana":"ｱﾂｹｼ"},{"code":"080","name":"標茶","name_kana":"ｼﾍﾞﾁﾔ"},{"code":"081","name":"弟子屈","name_kana":"ﾃｼｶｶﾞ"},{"code":"082","name":"根室","name_kana":"ﾈﾑﾛ"},{"code":"083","name":"中標津","name_kana":"ﾅｶｼﾍﾞﾂ"},{"code":"085","name":"留辺蘂","name_kana":"ﾙﾍﾞｼﾍﾞ"},{"code":"086","name":"美幌","name_kana":"ﾋﾞﾎﾛ"},{"code":"087","name":"網走","name_kana":"ｱﾊﾞｼﾘ"},{"code":"088","name":"遠軽","name_kana":"ｴﾝｶﾞﾙ"},{"code":"089","name":"紋別","name_kana":"ﾓﾝﾍﾞﾂ"},{"code":"090","name":"柏林台","name_kana":"ﾊｸﾘﾝﾀﾞｲ"},{"code":"091","name":"留萌","name_kana":"ﾙﾓｲ"},{"code":"092","name":"増毛","name_kana":"ﾏｼｹ"},{"code":"093","name":"西線","name_kana":"ﾆｼｾﾝ"},{"code":"094","name":"八軒","name_kana":"ﾊﾁｹﾝ"},{"code":"095","name":"菊水","name_kana":"ｷｸｽｲ"},{"code":"096","name":"稚内","name_kana":"ﾜﾂｶﾅｲ"},{"code":"097","name":"浜頓別","name_kana":"ﾊﾏﾄﾝﾍﾞﾂ"},{"code":"098","name":"日吉","name_kana":"ﾋﾖｼ"},{"code":"100","name":"東京","name_kana":"ﾄｳｷﾖｳ"},{"code":"103","name":"桑園","name_kana":"ｿｳｴﾝ"},{"code":"112","name":"西野二股","name_kana":"ﾆｼﾉﾌﾀﾏﾀ"},{"code":"114","name":"北野","name_kana":"ｷﾀﾉ"},{"code":"115","name":"札幌東","name_kana":"ｻﾂﾎﾟﾛﾋｶﾞｼ"},{"code":"117","name":"あいの里","name_kana":"ｱｲﾉｻﾄ"},{"code":"120","name":"元町","name_kana":"ﾓﾄﾏﾁ"},{"code":"121","name":"新川","name_kana":"ｼﾝｶﾜ"},{"code":"127","name":"旭ヶ丘","name_kana":"ｱｻﾋｶﾞｵｶ"},{"code":"130","name":"木野","name_kana":"ｷﾉ"},{"code":"131","name":"祝梅","name_kana":"ｼﾕｸﾊﾞｲ"},{"code":"134","name":"桔梗","name_kana":"ｷｷﾖｳ"},{"code":"137","name":"宮の沢","name_kana":"ﾐﾔﾉｻﾜ"},{"code":"138","name":"福住","name_kana":"ﾌｸｽﾞﾐ"},{"code":"139","name":"登別","name_kana":"ﾉﾎﾞﾘﾍﾞﾂ"},{"code":"140","name":"七重浜","name_kana":"ﾅﾅｴﾊﾏ"},{"code":"141","name":"沼ノ端","name_kana":"ﾇﾏﾉﾊﾀ"},{"code":"142","name":"平岡公園","name_kana":"ﾋﾗｵｶｺｳｴﾝ"},{"code":"143","name":"森林公園","name_kana":"ｼﾝﾘﾝｺｳｴﾝ"},{"code":"144","name":"帯広西","name_kana":"ｵﾋﾞﾋﾛﾆｼ"},{"code":"145","name":"神楽","name_kana":"ｶｸﾞﾗ"},{"code":"160","name":"菊水上町","name_kana":"ｷｸｽｲｶﾐﾏﾁ"},{"code":"161","name":"新手稲","name_kana":"ｼﾝﾃｲﾈ"},{"code":"173","name":"永山北","name_kana":"ﾅｶﾞﾔﾏｷﾀ"},{"code":"174","name":"当麻","name_kana":"ﾄｳﾏ"},{"code":"184","name":"北広島中央","name_kana":"ｷﾀﾋﾛｼﾏﾁﾕｳｵｳ"},{"code":"192","name":"手稲あけぼの","name_kana":"ﾃｲﾈｱｹﾎﾞﾉ"},{"code":"303","name":"札幌南","name_kana":"ｻﾂﾎﾟﾛﾐﾅﾐ"},{"code":"304","name":"札幌西","name_kana":"ｻﾂﾎﾟﾛﾆｼ"},{"code":"306","name":"東屯田","name_kana":"ﾋｶﾞｼﾄﾝﾃﾞﾝ"},{"code":"309","name":"苗穂","name_kana":"ﾅｴﾎﾞ"},{"code":"310","name":"札幌駅南口","name_kana":"ｻﾂﾎﾟﾛｴｷﾐﾅﾐｸﾞﾁ"},{"code":"311","name":"大曲","name_kana":"ｵｵﾏｶﾞﾘ"},{"code":"312","name":"北七条","name_kana":"ｷﾀﾅﾅｼﾞﾖｳ"},{"code":"313","name":"北五条通","name_kana":"ｷﾀｺﾞｼﾞﾖｳﾄﾞｵﾘ"},{"code":"314","name":"円山公園","name_kana":"ﾏﾙﾔﾏｺｳｴﾝ"},{"code":"315","name":"琴似中央","name_kana":"ｺﾄﾆﾁﾕｳｵｳ"},{"code":"317","name":"江別中央","name_kana":"ｴﾍﾞﾂﾁﾕｳｵｳ"},{"code":"318","name":"千歳中央","name_kana":"ﾁﾄｾﾁﾕｳｵｳ"},{"code":"319","name":"北二十四条","name_kana":"ｷﾀﾆｼﾞﾕｳﾖｼﾞﾖｳ"},{"code":"321","name":"函館中央","name_kana":"ﾊｺﾀﾞﾃﾁﾕｳｵｳ"},{"code":"322","name":"末広町","name_kana":"ｽｴﾋﾛﾁﾖｳ"},{"code":"323","name":"花川南","name_kana":"ﾊﾅｶﾜﾐﾅﾐ"},{"code":"324","name":"千歳富丘","name_kana":"ﾁﾄｾﾄﾐｵｶ"},{"code":"327","name":"万代町","name_kana":"ﾊﾞﾝﾀﾞｲﾁﾖｳ"},{"code":"328","name":"五稜郭公園","name_kana":"ｺﾞﾘﾖｳｶｸｺｳｴﾝ"},{"code":"329","name":"湯川","name_kana":"ﾕﾉｶﾜ"},{"code":"337","name":"美原","name_kana":"ﾐﾊﾗ"},{"code":"338","name":"西の里","name_kana":"ﾆｼﾉｻﾄ"},{"code":"339","name":"札苗","name_kana":"ｻﾂﾅｴ"},{"code":"341","name":"小樽中央","name_kana":"ｵﾀﾙﾁﾕｳｵｳ"},{"code":"345","name":"小樽駅前","name_kana":"ｵﾀﾙｴｷﾏｴ"},{"code":"346","name":"アルカ","name_kana":"ｱﾙｶ"},{"code":"349","name":"屯田北","name_kana":"ﾄﾝﾃﾞﾝｷﾀ"},{"code":"350","name":"奥沢口","name_kana":"ｵｸｻﾜｸﾞﾁ"},{"code":"354","name":"岩内中央","name_kana":"ｲﾜﾅｲﾁﾕｳｵｳ"},{"code":"361","name":"室蘭中央","name_kana":"ﾑﾛﾗﾝﾁﾕｳｵｳ"},{"code":"363","name":"中島町","name_kana":"ﾅｶｼﾞﾏﾁﾖｳ"},{"code":"371","name":"苫小牧中央","name_kana":"ﾄﾏｺﾏｲﾁﾕｳｵｳ"},{"code":"381","name":"岩見沢中央","name_kana":"ｲﾜﾐｻﾞﾜﾁﾕｳｵｳ"},{"code":"387","name":"夕張","name_kana":"ﾕｳﾊﾞﾘ"},{"code":"395","name":"赤平","name_kana":"ｱｶﾋﾞﾗ"},{"code":"396","name":"芦別","name_kana":"ｱｼﾍﾞﾂ"},{"code":"401","name":"旭川中央","name_kana":"ｱｻﾋｶﾜﾁﾕｳｵｳ"},{"code":"403","name":"大雪通","name_kana":"ﾀｲｾﾂﾄﾞｵﾘ"},{"code":"404","name":"永山中央","name_kana":"ﾅｶﾞﾔﾏﾁﾕｳｵｳ"},{"code":"408","name":"豊岡","name_kana":"ﾄﾖｵｶ"},{"code":"409","name":"春光","name_kana":"ｼﾕﾝｺｳ"},{"code":"423","name":"美深","name_kana":"ﾋﾞﾌｶ"},{"code":"424","name":"糸井","name_kana":"ｲﾄｲ"},{"code":"431","name":"帯広中央","name_kana":"ｵﾋﾞﾋﾛﾁﾕｳｵｳ"},{"code":"436","name":"幕別","name_kana":"ﾏｸﾍﾞﾂ"},{"code":"438","name":"本別","name_kana":"ﾎﾝﾍﾞﾂ"},{"code":"441","name":"釧路中央","name_kana":"ｸｼﾛﾁﾕｳｵｳ"},{"code":"448","name":"新橋大通","name_kana":"ｼﾝﾊﾞｼｵｵﾄﾞｵﾘ"},{"code":"450","name":"星置","name_kana":"ﾎｼｵｷ"},{"code":"451","name":"北見中央","name_kana":"ｷﾀﾐﾁﾕｳｵｳ"},{"code":"452","name":"斜里","name_kana":"ｼﾔﾘ"},{"code":"461","name":"澄川中央","name_kana":"ｽﾐｶﾜﾁﾕｳｵｳ"},{"code":"462","name":"栄町","name_kana":"ｻｶｴﾏﾁ"},{"code":"464","name":"新発寒","name_kana":"ｼﾝﾊﾂｻﾑ"},{"code":"468","name":"新川中央","name_kana":"ｼﾝｶﾜﾁﾕｳｵｳ"},{"code":"472","name":"恵庭中央","name_kana":"ｴﾆﾜﾁﾕｳｵｳ"},{"code":"473","name":"真駒内中央","name_kana":"ﾏｺﾏﾅｲﾁﾕｳｵｳ"},{"code":"474","name":"大谷地","name_kana":"ｵｵﾔﾁ"},{"code":"475","name":"道庁","name_kana":"ﾄﾞｳﾁﾖｳ"},{"code":"476","name":"白石中央","name_kana":"ｼﾛｲｼﾁﾕｳｵｳ"},{"code":"477","name":"月寒中央","name_kana":"ﾂｷｻﾑﾁﾕｳｵｳ"},{"code":"478","name":"石山通","name_kana":"ｲｼﾔﾏﾄﾞｵﾘ"},{"code":"480","name":"西町","name_kana":"ﾆｼﾏﾁ"},{"code":"481","name":"北十五条","name_kana":"ｷﾀｼﾞﾕｳｺﾞｼﾞﾖｳ"},{"code":"483","name":"平岸中央","name_kana":"ﾋﾗｷﾞｼﾁﾕｳｵｳ"},{"code":"484","name":"千歳空港出張所","name_kana":"ﾁﾄｾｸｳｺｳ"},{"code":"485","name":"札幌市役所","name_kana":"ｻﾂﾎﾟﾛｼﾔｸｼﾖ"},{"code":"486","name":"厚別中央","name_kana":"ｱﾂﾍﾞﾂﾁﾕｳｵｳ"},{"code":"487","name":"麻生","name_kana":"ｱｻﾌﾞ"},{"code":"488","name":"南郷通","name_kana":"ﾅﾝｺﾞｳﾄﾞｵﾘ"},{"code":"489","name":"伏古","name_kana":"ﾌｼｺ"},{"code":"490","name":"北都","name_kana":"ﾎｸﾄ"},{"code":"491","name":"手稲中央","name_kana":"ﾃｲﾈﾁﾕｳｵｳ"},{"code":"492","name":"花川北","name_kana":"ﾊﾅｶﾜｷﾀ"},{"code":"494","name":"藻岩","name_kana":"ﾓｲﾜ"},{"code":"495","name":"篠路","name_kana":"ｼﾉﾛ"},{"code":"496","name":"野幌中央","name_kana":"ﾉﾂﾎﾟﾛﾁﾕｳｵｳ"},{"code":"497","name":"清田区役所前","name_kana":"ｷﾖﾀｸﾔｸｼﾖﾏｴ"},{"code":"701","name":"はまなす","name_kana":"ﾊﾏﾅｽ"}]