[{"code":"001","name":"本店","name_kana":"ﾎﾝﾃﾝ"},{"code":"002","name":"阿南","name_kana":"ｱﾅﾝ"},{"code":"003","name":"鳴門","name_kana":"ﾅﾙﾄ"},{"code":"004","name":"池田","name_kana":"ｲｹﾀﾞ"},{"code":"005","name":"牟岐","name_kana":"ﾑｷﾞ"},{"code":"006","name":"小松島","name_kana":"ｺﾏﾂｼﾏ"},{"code":"007","name":"市場","name_kana":"ｲﾁﾊﾞ"},{"code":"008","name":"中島","name_kana":"ﾅｶｼﾏ"},{"code":"009","name":"鴨島","name_kana":"ｶﾓｼﾞﾏ"},{"code":"010","name":"穴吹","name_kana":"ｱﾅﾌﾞｷ"},{"code":"011","name":"板野","name_kana":"ｲﾀﾉ"},{"code":"013","name":"勝浦","name_kana":"ｶﾂｳﾗ"},{"code":"014","name":"高松","name_kana":"ﾀｶﾏﾂ"},{"code":"015","name":"高知","name_kana":"ｺｳﾁ"},{"code":"016","name":"日和佐","name_kana":"ﾋﾜｻ"},{"code":"017","name":"洲本","name_kana":"ｽﾓﾄ"},{"code":"018","name":"佐古","name_kana":"ｻｺ"},{"code":"019","name":"丸亀","name_kana":"ﾏﾙｶﾞﾒ"},{"code":"021","name":"三野","name_kana":"ﾐﾉ"},{"code":"023","name":"鷲敷","name_kana":"ﾜｼﾞｷ"},{"code":"024","name":"北島","name_kana":"ｷﾀｼﾞﾏ"},{"code":"025","name":"石井","name_kana":"ｲｼｲ"},{"code":"026","name":"橘","name_kana":"ﾀﾁﾊﾞﾅ"},{"code":"029","name":"渭東","name_kana":"ｲﾄｳ"},{"code":"030","name":"南あわじ","name_kana":"ﾐﾅﾐｱﾜｼﾞ"},{"code":"031","name":"海部","name_kana":"ｶｲﾌ"},{"code":"032","name":"渭北","name_kana":"ｲﾎｸ"},{"code":"033","name":"昭和町","name_kana":"ｼﾖｳﾜﾁﾖｳ"},{"code":"034","name":"二軒屋","name_kana":"ﾆｹﾝﾔ"},{"code":"035","name":"松山","name_kana":"ﾏﾂﾔﾏ"},{"code":"036","name":"徳島駅前","name_kana":"ﾄｸｼﾏｴｷﾏｴ"},{"code":"037","name":"大阪","name_kana":"ｵｵｻｶ"},{"code":"038","name":"国府","name_kana":"ｺｸﾌ"},{"code":"039","name":"助任","name_kana":"ｽｹﾄｳ"},{"code":"040","name":"津田","name_kana":"ﾂﾀﾞ"},{"code":"041","name":"八万","name_kana":"ﾊﾁﾏﾝ"},{"code":"042","name":"加茂名","name_kana":"ｶﾓﾅ"},{"code":"043","name":"沖洲","name_kana":"ｵｷﾉｽ"},{"code":"044","name":"佐古東","name_kana":"ｻｺﾋｶﾞｼ"},{"code":"045","name":"羽ノ浦団地","name_kana":"ﾊﾉｳﾗﾀﾞﾝﾁ"},{"code":"046","name":"南昭和町","name_kana":"ﾐﾅﾐｼﾖｳﾜﾁﾖｳ"},{"code":"047","name":"藍住","name_kana":"ｱｲｽﾞﾐ"},{"code":"048","name":"南小松島","name_kana":"ﾐﾅﾐｺﾏﾂｼﾏ"},{"code":"049","name":"川内","name_kana":"ｶﾜｳﾁ"},{"code":"050","name":"矢三","name_kana":"ﾔｿ"},{"code":"051","name":"阿北","name_kana":"ｱﾎｸ"},{"code":"052","name":"堺","name_kana":"ｻｶｲ"},{"code":"054","name":"脇町","name_kana":"ﾜｷﾏﾁ"},{"code":"055","name":"宝田","name_kana":"ﾀｶﾗﾀﾞ"},{"code":"056","name":"地蔵橋","name_kana":"ﾁﾞｿﾞｳﾊﾞｼ"},{"code":"057","name":"流通センター","name_kana":"ﾘﾕｳﾂｳｾﾝﾀ-"},{"code":"058","name":"今治","name_kana":"ｲﾏﾊﾞﾘ"},{"code":"059","name":"鳴門東","name_kana":"ﾅﾙﾄﾋｶﾞｼ"},{"code":"060","name":"大麻","name_kana":"ｵｵｱｻ"},{"code":"061","name":"上板","name_kana":"ｶﾐｲﾀ"},{"code":"062","name":"県庁","name_kana":"ｹﾝﾁﾖｳ"},{"code":"063","name":"貞光","name_kana":"ｻﾀﾞﾐﾂ"},{"code":"064","name":"論田","name_kana":"ﾛﾝﾃﾞﾝ"},{"code":"065","name":"三加茂","name_kana":"ﾐｶﾓ"},{"code":"066","name":"東京","name_kana":"ﾄｳｷﾖｳ"},{"code":"067","name":"空港","name_kana":"ｸｳｺｳ"},{"code":"068","name":"国府北","name_kana":"ｺｸﾌｷﾀ"},{"code":"069","name":"弁天町","name_kana":"ﾍﾞﾝﾃﾝﾁﾖｳ"},{"code":"070","name":"勝瑞","name_kana":"ｼﾖｳｽﾞｲ"},{"code":"071","name":"山川","name_kana":"ﾔﾏｶﾜ"},{"code":"072","name":"桑野","name_kana":"ｸﾜﾉ"},{"code":"073","name":"マリンピア","name_kana":"ﾏﾘﾝﾋﾟｱ"},{"code":"074","name":"神戸","name_kana":"ｺｳﾍﾞ"},{"code":"075","name":"阿波町","name_kana":"ｱﾜﾁﾖｳ"},{"code":"076","name":"東大阪","name_kana":"ﾋｶﾞｼｵｵｻｶ"},{"code":"077","name":"江坂","name_kana":"ｴｻｶ"},{"code":"078","name":"南森町","name_kana":"ﾐﾅﾐﾓﾘﾏﾁ"},{"code":"079","name":"尼崎","name_kana":"ｱﾏｶﾞｻｷ"},{"code":"080","name":"蒲田","name_kana":"ｶﾏﾀ"},{"code":"081","name":"亀戸","name_kana":"ｶﾒｲﾄﾞ"},{"code":"082","name":"池袋","name_kana":"ｲｹﾌﾞｸﾛ"}]