[{"code":"004","name":"大宮","name_kana":"ｵｵﾐﾔ"},{"code":"008","name":"大野","name_kana":"ｵｵﾉ"},{"code":"010","name":"卸本町","name_kana":"ｵﾛｼﾎﾝﾏﾁ"},{"code":"076","name":"大野中央","name_kana":"ｵｵﾉﾁﾕｳｵｳ"},{"code":"102","name":"大波止","name_kana":"ｵｵﾊﾄ"},{"code":"108","name":"大浦","name_kana":"ｵｵｳﾗ"},{"code":"201","name":"大瀬戸","name_kana":"ｵｵｾﾄ"},{"code":"203","name":"大崎","name_kana":"ｵｵｻｷ"},{"code":"204","name":"大串","name_kana":"ｵｵｸｼ"},{"code":"401","name":"大村","name_kana":"ｵｵﾑﾗ"},{"code":"601","name":"小値賀","name_kana":"ｵﾁﾞｶ"}]